use_notify/__init__.py
use_notify/channels/__init__.py
use_notify/channels/bark.py
use_notify/channels/base.py
use_notify/channels/chanify.py
use_notify/channels/console.py
use_notify/channels/ding.py
use_notify/channels/email.py
use_notify/channels/feishu.py
use_notify/channels/pushdeer.py
use_notify/channels/pushover.py
use_notify/channels/wechat.py
use_notify/decorator/__init__.py
use_notify/decorator/context.py
use_notify/decorator/core.py
use_notify/decorator/exceptions.py
use_notify/decorator/formatter.py
use_notify/decorator/sender.py
use_notify/notification.py
use_notify-0.3.44.dist-info/METADATA
use_notify-0.3.44.dist-info/WHEEL
use_notify-0.3.44.dist-info/RECORD
