Metadata-Version: 2.1
Name: use-notify
Version: 0.3.44
Summary: 一个简单可扩展的异步消息通知库
Author: miclon
Author-email: jcnd@163.com
Requires-Python: >=3.8,<4.0
Classifier: Programming Language :: Python :: 3
Classifier: Programming Language :: Python :: 3.8
Classifier: Programming Language :: Python :: 3.9
Classifier: Programming Language :: Python :: 3.10
Classifier: Programming Language :: Python :: 3.11
Classifier: Programming Language :: Python :: 3.12
Requires-Dist: httpx
Requires-Dist: usepy (>=0.4.0,<0.5.0)
